LICENCE.txt
MANIFEST.in
README.md
requirements-dev.txt
requirements-extra.txt
requirements.txt
setup.py
mlexp/__init__.py
mlexp.egg-info/PKG-INFO
mlexp.egg-info/SOURCES.txt
mlexp.egg-info/dependency_links.txt
mlexp.egg-info/requires.txt
mlexp.egg-info/top_level.txt
mlexp/inference/__init__.py
mlexp/inference/lgb_inference.py
mlexp/inference/sklearn_inference.py
mlexp/inference/torch_inference.py
mlexp/inference/_base_inference/__init__.py
mlexp/inference/_base_inference/_base_inference.py
mlexp/inference/_base_inference/_mlflow_inference.py
mlexp/inference/_base_inference/_neptune_inference.py
mlexp/trainers/__init__.py
mlexp/trainers/_base_logger.py
mlexp/trainers/_base_trainer.py
mlexp/trainers/_utils.py
mlexp/trainers/lgb_trainer.py
mlexp/trainers/sklearn_trainer.py
mlexp/trainers/torch_trainer.py
tests/test_inference/__init__.py
tests/test_inference/test_inference.py
tests/test_inference/utils.py
tests/test_trainers/__init__.py
tests/test_trainers/params_funcs.py
tests/test_trainers/test_trainers.py
tests/test_trainers/utils.py
tests/test_trainers/torch_utils/__init__.py
tests/test_trainers/torch_utils/data_loaders.py
tests/test_trainers/torch_utils/metrics_callback.py
tests/test_trainers/torch_utils/nn_model.py