Metadata-Version: 2.1
Name: mlexp
Version: 0.0.3
Summary: MLexp allows to train different types of machine learning models,                  optimize hyperparameters and log results with simple API
Home-page: UNKNOWN
Author: Ilia Avilov
Author-email: ieavilov@gmail.com
License: MIT
Project-URL: GitHub, https://github.com/volico/mlexp
Keywords: machine learning
Platform: UNKNOWN
Classifier: License :: OSI Approved :: MIT License
Classifier: Intended Audience :: Science/Research
Classifier: Intended Audience :: Developers
Classifier: Topic :: Software Development
Classifier: Topic :: Scientific/Engineering
Classifier: Operating System :: Unix
Classifier: Operating System :: Microsoft :: Windows
Classifier: Operating System :: MacOS
Classifier: Operating System :: POSIX
Classifier: Programming Language :: Python
Classifier: Programming Language :: Python :: 3.9
Requires-Python: >=3.9
Provides-Extra: torch
License-File: LICENCE.txt
